azure/azure.py
azure/manifest.toml
azure/test_azure.py
opsbox_azure_output-0.1.4.dist-info/LICENCE.txt
opsbox_azure_output-0.1.4.dist-info/METADATA
opsbox_azure_output-0.1.4.dist-info/WHEEL
opsbox_azure_output-0.1.4.dist-info/entry_points.txt
opsbox_azure_output-0.1.4.dist-info/top_level.txt
opsbox_azure_output-0.1.4.dist-info/RECORD
