Metadata-Version: 2.2
Name: opsbox-azure-output
Version: 0.1.4
Summary: Azure issues output for opsbox
Requires-Python: ==3.11.*
License-File: LICENCE.txt
Requires-Dist: llama-index>=0.12.6
Requires-Dist: loguru>=0.7.2
Requires-Dist: pandas>=2.2.3
Requires-Dist: markdown>=3.7
Requires-Dist: pluggy>=1.5.0
Requires-Dist: pydantic>=2.10.2
Requires-Dist: requests>=2.32.3
Requires-Dist: opsbox-general-handler>=0.1.2
